MANIFEST.in
README.md
requirements.txt
setup.cfg
setup.py
wrapml/__init__.py
wrapml/constants.py
wrapml/exceptions.py
wrapml.egg-info/PKG-INFO
wrapml.egg-info/SOURCES.txt
wrapml.egg-info/dependency_links.txt
wrapml.egg-info/not-zip-safe
wrapml.egg-info/requires.txt
wrapml.egg-info/top_level.txt
wrapml/data_generator/__init__.py
wrapml/data_generator/data_generator.py
wrapml/data_generator/utils.py
wrapml/data_generator/tests/__init__.py
wrapml/data_generator/tests/test_data_generator.py
wrapml/imports/__init__.py
wrapml/imports/db.py
wrapml/imports/learn.py
wrapml/imports/science.py
wrapml/imports/testing.py
wrapml/imports/vanilla.py
wrapml/learn/__init__.py
wrapml/learn/reinforcement/__init__.py
wrapml/learn/supervised/__init__.py
wrapml/learn/supervised/classification/__init__.py
wrapml/learn/supervised/classification/classification.py
wrapml/learn/supervised/classification/tests/__init__.py
wrapml/learn/supervised/classification/tests/test_classification.py
wrapml/learn/supervised/regression/__init__.py
wrapml/learn/supervised/regression/regression.py
wrapml/learn/supervised/segmentation/__init__.py
wrapml/learn/supervised/segmentation/segmentation.py
wrapml/learn/unsupervised/__init__.py
wrapml/learn/unsupervised/anomaly_detection/__init__.py
wrapml/learn/unsupervised/anomaly_detection/anomaly_detection.py
wrapml/learn/unsupervised/clustering/__init__.py
wrapml/playground/__init__.py
wrapml/playground/play_with_churn.py
wrapml/playground/play_with_ltsm.py
wrapml/plots/__init__.py
wrapml/plots/plots.py
wrapml/utils/__init__.py
wrapml/utils/logging.py