Metadata-Version: 2.1
Name: wrapml
Version: 0.0.19
Summary: Simplifying ML.
Home-page: https://github.com/bugo99iot/wrapml
Author: Ugo Bee
Author-email: ugo.bertello@gmail.com
License: MIT
Keywords: machine learning,deep learning
Platform: UNKNOWN
Classifier: Programming Language :: Python :: 3.6
Requires-Python: >=3.6
